travel_salesman/__init__.py
travel_salesman/tsp.py
travel_salesman-0.1.0.dist-info/LICENSE
travel_salesman-0.1.0.dist-info/METADATA
travel_salesman-0.1.0.dist-info/WHEEL
travel_salesman-0.1.0.dist-info/RECORD
