Metadata-Version: 2.1
Name: travel-salesman
Version: 0.1.0
Summary: 
Author: amirbahador
Author-email: amirbahador.pv@gmail.com
Requires-Python: ==3.10.9
Classifier: Programming Language :: Python :: 3
Requires-Dist: ortools (>=9.6.2534,<10.0.0)
